MANIFEST.in
README.rst
bootstrap-buildout.py
buildout-before-patch.cfg
buildout.cfg
requirements.txt
setup.py
version.txt
bob/__init__.py
bob.bio.csu.egg-info/PKG-INFO
bob.bio.csu.egg-info/SOURCES.txt
bob.bio.csu.egg-info/dependency_links.txt
bob.bio.csu.egg-info/entry_points.txt
bob.bio.csu.egg-info/requires.txt
bob.bio.csu.egg-info/top_level.txt
bob/bio/__init__.py
bob/bio/csu/__init__.py
bob/bio/csu/algorithm/LDAIR.py
bob/bio/csu/algorithm/LRPCA.py
bob/bio/csu/algorithm/__init__.py
bob/bio/csu/config/__init__.py
bob/bio/csu/config/algorithm/__init__.py
bob/bio/csu/config/algorithm/ldair.py
bob/bio/csu/config/algorithm/lrpca.py
bob/bio/csu/config/extractor/__init__.py
bob/bio/csu/config/extractor/ldair.py
bob/bio/csu/config/extractor/lrpca.py
bob/bio/csu/config/preprocessor/__init__.py
bob/bio/csu/config/preprocessor/ldair.py
bob/bio/csu/config/preprocessor/lrpca.py
bob/bio/csu/extractor/LDAIR.py
bob/bio/csu/extractor/LRPCA.py
bob/bio/csu/extractor/__init__.py
bob/bio/csu/preprocessor/LDAIR.py
bob/bio/csu/preprocessor/LRPCA.py
bob/bio/csu/preprocessor/__init__.py
bob/bio/csu/test/__init__.py
bob/bio/csu/test/test_algorithms.py
bob/bio/csu/test/test_extractors.py
bob/bio/csu/test/test_preprocessors.py
bob/bio/csu/test/data/ldair_detected.hdf5
bob/bio/csu/test/data/ldair_extracted.hdf5
bob/bio/csu/test/data/ldair_extractor.hdf5
bob/bio/csu/test/data/ldair_model.hdf5
bob/bio/csu/test/data/ldair_preprocessed.hdf5
bob/bio/csu/test/data/lrpca_detected.hdf5
bob/bio/csu/test/data/lrpca_extracted.hdf5
bob/bio/csu/test/data/lrpca_extractor.hdf5
bob/bio/csu/test/data/lrpca_model.hdf5
bob/bio/csu/test/data/lrpca_preprocessed.hdf5
bob/bio/csu/utils/__init__.py
doc/conf.py
doc/implemented.rst
doc/index.rst
doc/installation.rst
doc/links.rst
patch/__init__.py
patch/bob.bio.csu.patch