Metadata-Version: 1.1
Name: bob.bio.csu
Version: 2.0.4
Summary: Wrapper classes to use the PythonFaceEvaluation classes from the CSU Face Recognition Resources
Home-page: https://www.github.com/<YourInstitution>/<YourPackage>
Author: <YourName>
Author-email: <YourEmail>
License: GPLv3
Keywords: bob
Platform: UNKNOWN
Classifier: Framework :: Bob
Classifier: Development Status :: 3 - Alpha
Classifier: Intended Audience :: Developers
Classifier: License :: OSI Approved :: GNU General Public License v3 (GPLv3)
Classifier: Natural Language :: English
Classifier: Programming Language :: Python
Classifier: Topic :: Scientific/Engineering :: Artificial Intelligence
